ntbk/__init__.py
ntbk/config.py
ntbk/dispatcher.py
ntbk/exceptions.py
ntbk/filesystem.py
ntbk/helpers.py
ntbk/initialize.py
ntbk/main.py
ntbk/entities/__init__.py
ntbk/entities/collections.py
ntbk/entities/logs.py
ntbk/entities/notebook.py
ntbk/entities/templates.py
tests/__init__.py
tests/conftest.py
tests/feature/__init__.py
tests/feature/test_collection_commands.py
tests/feature/test_initialization.py
tests/feature/test_listing.py
tests/feature/test_log_commands.py
tests/feature/test_templates.py
tests/unit/__init__.py
tests/unit/test_helpers.py
ntbk-0.2.0.dist-info/LICENSE
ntbk-0.2.0.dist-info/METADATA
ntbk-0.2.0.dist-info/WHEEL
ntbk-0.2.0.dist-info/entry_points.txt
ntbk-0.2.0.dist-info/top_level.txt
ntbk-0.2.0.dist-info/RECORD
