Metadata-Version: 2.1
Name: ntbk
Version: 0.2.0
Summary: A simple, opinionated terminal notebook inspired by bullet journaling.
Home-page: https://github.com/bbeng89/ntbk
Author: Blake Bengtson
Author-email: blake@bengtson.us
License: MIT
Platform: UNKNOWN
Classifier: Development Status :: 4 - Beta
Classifier: Environment :: Console
Classifier: Intended Audience :: End Users/Desktop
Classifier: License :: OSI Approved :: MIT License
Classifier: Operating System :: OS Independent
Classifier: Programming Language :: Python :: 3.7
Classifier: Topic :: Utilities
Requires-Python: >=3.7
License-File: LICENSE
Requires-Dist: astroid (==2.9.0)
Requires-Dist: attrs (==21.2.0)
Requires-Dist: colorama (==0.4.4)
Requires-Dist: freezegun (==1.1.0)
Requires-Dist: iniconfig (==1.1.1)
Requires-Dist: isort (==5.10.1)
Requires-Dist: Jinja2 (==3.0.3)
Requires-Dist: lazy-object-proxy (==1.7.1)
Requires-Dist: MarkupSafe (==2.0.1)
Requires-Dist: mccabe (==0.6.1)
Requires-Dist: packaging (==21.3)
Requires-Dist: platformdirs (==2.4.0)
Requires-Dist: pluggy (==1.0.0)
Requires-Dist: py (==1.11.0)
Requires-Dist: pydantic (==1.7.4)
Requires-Dist: pylint (==2.12.2)
Requires-Dist: pyparsing (==3.0.6)
Requires-Dist: pytest (==6.2.5)
Requires-Dist: pytest-mock (==3.6.1)
Requires-Dist: python-dateutil (==2.8.2)
Requires-Dist: PyYAML (==6.0)
Requires-Dist: six (==1.16.0)
Requires-Dist: toml (==0.10.2)
Requires-Dist: typing-extensions (==4.0.1)
Requires-Dist: wrapt (==1.13.3)
